{"2020-12-30": {"count": 0, "versions": {}}, "2020-12-31": {"count": 0, "versions": {}}, "2021-03-28": {"count": 0, "versions": {}}, "2021-03-29": {"count": 0, "versions": {}}, "2021-03-26": {"count": 0, "versions": {}}, "2021-03-27": {"count": 0, "versions": {}}, "2021-03-24": {"count": 0, "versions": {}}, "2021-03-25": {"count": 0, "versions": {}}, "2021-03-22": {"count": 0, "versions": {}}, "2021-03-23": {"count": 0, "versions": {}}, "2021-03-20": {"count": 0, "versions": {}}, "2021-03-21": {"count": 0, "versions": {}}, "2021-01-19": {"count": 0, "versions": {}}, "2021-01-18": {"count": 0, "versions": {}}, "2021-01-11": {"count": 0, "versions": {}}, "2021-01-10": {"count": 0, "versions": {}}, "2021-01-13": {"count": 0, "versions": {}}, "2021-01-12": {"count": 0, "versions": {}}, "2021-01-15": {"count": 0, "versions": {}}, "2021-01-14": {"count": 0, "versions": {}}, "2021-01-17": {"count": 0, "versions": {}}, "2021-01-16": {"count": 0, "versions": {}}, "2021-05-06": {"count": 0, "versions": {}}, "2021-05-07": {"count": 0, "versions": {}}, "2021-05-04": {"count": 0, "versions": {}}, "2021-05-05": {"count": 0, "versions": {}}, "2021-05-02": {"count": 0, "versions": {}}, "2021-05-03": {"count": 0, "versions": {}}, "2021-05-01": {"count": 0, "versions": {}}, "2021-05-08": {"count": 0, "versions": {}}, "2021-05-09": {"count": 0, "versions": {}}, "2021-09-11": {"count": 29197, "versions": {"94.0a1": 3967, "93.0a1": 1147, "92.0a1": 91, "92.0": 15674, "93.0": 8318}}, "2021-09-10": {"count": 43828, "versions": {"2021.03": 1, "93.0a1": 1432, "92.0a1": 110, "93.0": 3425, "94.0a1": 4857, "92.0": 34003}}, "2021-09-13": {"count": 46992, "versions": {"2021.03": 5, "93.0a1": 1022, "92.0a1": 121, "93.0": 24767, "94.0a1": 5472, "92.0": 15605}}, "2021-09-12": {"count": 27646, "versions": {"92.0a1": 92, "94.0a1": 3815, "93.0a1": 1008, "92.0": 10409, "93.0": 12322}}, "2021-09-15": {"count": 46046, "versions": {"2021.03": 5, "93.0a1": 657, "92.0a1": 78, "93.0": 33483, "94.0a1": 5612, "92.0": 6211}}, "2021-09-14": {"count": 47349, "versions": {"2021.02": 4, "2021.03": 18, "93.0a1": 897, "92.0a1": 94, "93.0": 31736, "94.0a1": 5706, "92.0": 8894}}, "2021-09-17": {"count": 43968, "versions": {"94.0a1": 5879, "93.0a1": 363, "92.0a1": 61, "92.0": 3667, "93.0": 33998}}, "2021-09-16": {"count": 46030, "versions": {"94.0a1": 5765, "93.0a1": 430, "92.0a1": 76, "92.0": 4775, "93.0": 34984}}, "2021-09-19": {"count": 27216, "versions": {"94.0a1": 4467, "93.0a1": 232, "92.0a1": 44, "92.0": 2139, "93.0": 20334}}, "2021-09-18": {"count": 29605, "versions": {"94.0a1": 4780, "93.0a1": 253, "92.0a1": 52, "92.0": 2396, "93.0": 22124}}, "2021-02-14": {"count": 0, "versions": {}}, "2021-02-15": {"count": 3, "versions": {"611.7.0": 3}}, "2021-02-16": {"count": 0, "versions": {}}, "2021-02-17": {"count": 0, "versions": {}}, "2021-02-10": {"count": 0, "versions": {}}, "2021-02-11": {"count": 0, "versions": {}}, "2021-02-12": {"count": 0, "versions": {}}, "2021-02-13": {"count": 0, "versions": {}}, "2021-02-18": {"count": 0, "versions": {}}, "2021-02-19": {"count": 0, "versions": {}}, "2021-08-09": {"count": 6331, "versions": {"92.0a1": 6331}}, "2021-08-08": {"count": 4950, "versions": {"92.0a1": 4950}}, "2021-08-05": {"count": 6428, "versions": {"92.0a1": 6427, "7846.0": 1}}, "2021-08-04": {"count": 6486, "versions": {"92.0a1": 6486}}, "2021-08-07": {"count": 4993, "versions": {"92.0a1": 4993}}, "2021-08-06": {"count": 6032, "versions": {"92.0a1": 6032}}, "2021-08-01": {"count": 4876, "versions": {"92.0a1": 4876}}, "2021-08-03": {"count": 6182, "versions": {"92.0a1": 6182}}, "2021-08-02": {"count": 6044, "versions": {"92.0a1": 6044}}, "2020-10-23": {"count": 0, "versions": {}}, "2020-10-22": {"count": 0, "versions": {}}, "2020-10-21": {"count": 0, "versions": {}}, "2020-10-20": {"count": 4, "versions": {"6872.0": 1, "6852.0": 1, "6832.1": 2}}, "2020-10-27": {"count": 0, "versions": {}}, "2020-10-26": {"count": 0, "versions": {}}, "2019-12-30": {"count": 0, "versions": {}}, "2019-12-31": {"count": 0, "versions": {}}, "2020-10-29": {"count": 0, "versions": {}}, "2020-10-28": {"count": 0, "versions": {}}, "2021-06-07": {"count": 0, "versions": {}}, "2020-03-05": {"count": 0, "versions": {}}, "2021-06-05": {"count": 0, "versions": {}}, "2021-06-04": {"count": 0, "versions": {}}, "2021-06-03": {"count": 0, "versions": {}}, "2021-06-02": {"count": 0, "versions": {}}, "2020-08-28": {"count": 0, "versions": {}}, "2020-08-29": {"count": 0, "versions": {}}, "2020-08-26": {"count": 0, "versions": {}}, "2020-08-27": {"count": 0, "versions": {}}, "2020-08-24": {"count": 0, "versions": {}}, "2020-08-25": {"count": 0, "versions": {}}, "2020-08-22": {"count": 0, "versions": {}}, "2020-08-23": {"count": 0, "versions": {}}, "2020-08-20": {"count": 0, "versions": {}}, "2020-08-21": {"count": 0, "versions": {}}, "2020-01-18": {"count": 0, "versions": {}}, "2020-01-19": {"count": 0, "versions": {}}, "2020-01-14": {"count": 0, "versions": {}}, "2020-01-15": {"count": 0, "versions": {}}, "2020-01-16": {"count": 0, "versions": {}}, "2020-01-17": {"count": 0, "versions": {}}, "2020-01-10": {"count": 0, "versions": {}}, "2020-01-11": {"count": 0, "versions": {}}, "2020-01-12": {"count": 0, "versions": {}}, "2020-01-13": {"count": 0, "versions": {}}, "2021-04-28": {"count": 0, "versions": {}}, "2020-04-13": {"count": 0, "versions": {}}, "2020-07-09": {"count": 0, "versions": {}}, "2020-07-08": {"count": 0, "versions": {}}, "2020-07-01": {"count": 0, "versions": {}}, "2020-07-03": {"count": 0, "versions": {}}, "2020-07-02": {"count": 0, "versions": {}}, "2020-07-05": {"count": 0, "versions": {}}, "2020-07-04": {"count": 0, "versions": {}}, "2020-07-07": {"count": 0, "versions": {}}, "2020-07-06": {"count": 0, "versions": {}}, "2021-04-23": {"count": 0, "versions": {}}, "2021-04-22": {"count": 0, "versions": {}}, "2020-06-19": {"count": 0, "versions": {}}, "2020-11-21": {"count": 0, "versions": {}}, "2021-04-21": {"count": 0, "versions": {}}, "2019-10-26": {"count": 0, "versions": {}}, "2021-04-27": {"count": 5, "versions": {"2021.02": 5}}, "2021-04-26": {"count": 0, "versions": {}}, "2020-04-22": {"count": 0, "versions": {}}, "2020-04-23": {"count": 0, "versions": {}}, "2020-04-20": {"count": 0, "versions": {}}, "2020-04-21": {"count": 0, "versions": {}}, "2020-04-26": {"count": 0, "versions": {}}, "2020-04-27": {"count": 0, "versions": {}}, "2020-04-24": {"count": 0, "versions": {}}, "2020-04-25": {"count": 0, "versions": {}}, "2020-04-28": {"count": 0, "versions": {}}, "2020-04-29": {"count": 0, "versions": {}}, "2020-06-17": {"count": 0, "versions": {}}, "2020-06-16": {"count": 0, "versions": {}}, "2020-11-30": {"count": 0, "versions": {}}, "2020-02-11": {"count": 0, "versions": {}}, "2020-02-10": {"count": 0, "versions": {}}, "2020-02-13": {"count": 0, "versions": {}}, "2020-02-12": {"count": 0, "versions": {}}, "2020-02-15": {"count": 0, "versions": {}}, "2020-02-14": {"count": 0, "versions": {}}, "2020-02-17": {"count": 0, "versions": {}}, "2020-02-16": {"count": 0, "versions": {}}, "2020-02-19": {"count": 0, "versions": {}}, "2020-02-18": {"count": 0, "versions": {}}, "2020-09-14": {"count": 0, "versions": {}}, "2020-09-15": {"count": 0, "versions": {}}, "2020-09-16": {"count": 0, "versions": {}}, "2020-09-17": {"count": 0, "versions": {}}, "2020-09-10": {"count": 0, "versions": {}}, "2020-09-11": {"count": 0, "versions": {}}, "2020-09-12": {"count": 0, "versions": {}}, "2020-09-13": {"count": 0, "versions": {}}, "2020-09-18": {"count": 0, "versions": {}}, "2020-09-19": {"count": 0, "versions": {}}, "2020-03-09": {"count": 0, "versions": {}}, "2020-03-08": {"count": 0, "versions": {}}, "2021-09-26": {"count": 28439, "versions": {"92.0a1": 52, "94.0a1": 5076, "93.0a1": 166, "92.0": 1108, "93.0": 22037}}, "2020-03-04": {"count": 0, "versions": {}}, "2020-03-07": {"count": 0, "versions": {}}, "2020-03-06": {"count": 0, "versions": {}}, "2020-03-01": {"count": 0, "versions": {}}, "2020-03-03": {"count": 0, "versions": {}}, "2020-03-02": {"count": 0, "versions": {}}, "2019-10-23": {"count": 0, "versions": {}}, "2019-10-22": {"count": 0, "versions": {}}, "2019-10-21": {"count": 0, "versions": {}}, "2019-10-20": {"count": 0, "versions": {}}, "2019-10-27": {"count": 0, "versions": {}}, "2020-06-18": {"count": 0, "versions": {}}, "2019-10-25": {"count": 0, "versions": {}}, "2019-10-24": {"count": 0, "versions": {}}, "2020-06-15": {"count": 0, "versions": {}}, "2020-06-14": {"count": 0, "versions": {}}, "2019-10-29": {"count": 0, "versions": {}}, "2019-10-28": {"count": 0, "versions": {}}, "2020-06-11": {"count": 0, "versions": {}}, "2020-06-10": {"count": 0, "versions": {}}, "2020-06-13": {"count": 0, "versions": {}}, "2020-06-12": {"count": 0, "versions": {}}, "2021-09-27": {"count": 47372, "versions": {"94.0a1": 6275, "93.0a1": 243, "92.0a1": 41, "92.0": 1706, "93.0": 39107}}, "2021-07-31": {"count": 4834, "versions": {"92.0a1": 4834}}, "2021-07-30": {"count": 6005, "versions": {"92.0a1": 6005}}, "2020-05-18": {"count": 0, "versions": {}}, "2020-05-19": {"count": 0, "versions": {}}, "2020-05-10": {"count": 0, "versions": {}}, "2020-05-11": {"count": 0, "versions": {}}, "2020-05-12": {"count": 0, "versions": {}}, "2020-05-13": {"count": 0, "versions": {}}, "2020-05-14": {"count": 0, "versions": {}}, "2020-05-15": {"count": 0, "versions": {}}, "2020-05-16": {"count": 0, "versions": {}}, "2020-05-17": {"count": 0, "versions": {}}, "2021-04-02": {"count": 0, "versions": {}}, "2020-05-25": {"count": 0, "versions": {}}, "2020-10-18": {"count": 0, "versions": {}}, "2020-10-19": {"count": 0, "versions": {}}, "2019-11-30": {"count": 0, "versions": {}}, "2020-10-12": {"count": 0, "versions": {}}, "2020-10-13": {"count": 0, "versions": {}}, "2020-10-10": {"count": 0, "versions": {}}, "2020-10-11": {"count": 0, "versions": {}}, "2020-10-16": {"count": 0, "versions": {}}, "2020-10-17": {"count": 0, "versions": {}}, "2020-10-14": {"count": 0, "versions": {}}, "2020-10-15": {"count": 0, "versions": {}}, "2021-06-25": {"count": 0, "versions": {}}, "2020-11-23": {"count": 0, "versions": {}}, "2020-05-21": {"count": 0, "versions": {}}, "2021-06-30": {"count": 0, "versions": {}}, "2020-11-25": {"count": 0, "versions": {}}, "2019-09-14": {"count": 0, "versions": {}}, "2019-09-15": {"count": 0, "versions": {}}, "2019-09-16": {"count": 0, "versions": {}}, "2019-09-17": {"count": 0, "versions": {}}, "2019-09-10": {"count": 0, "versions": {}}, "2019-09-11": {"count": 0, "versions": {}}, "2019-09-12": {"count": 0, "versions": {}}, "2019-09-13": {"count": 0, "versions": {}}, "2021-06-21": {"count": 0, "versions": {}}, "2020-11-27": {"count": 0, "versions": {}}, "2019-09-18": {"count": 0, "versions": {}}, "2019-09-19": {"count": 0, "versions": {}}, "2019-09-06": {"count": 0, "versions": {}}, "2020-03-19": {"count": 0, "versions": {}}, "2021-06-23": {"count": 0, "versions": {}}, "2021-06-22": {"count": 0, "versions": {}}, "2020-12-25": {"count": 0, "versions": {}}, "2020-12-24": {"count": 0, "versions": {}}, "2020-12-27": {"count": 0, "versions": {}}, "2020-12-26": {"count": 0, "versions": {}}, "2020-12-21": {"count": 0, "versions": {}}, "2020-12-20": {"count": 0, "versions": {}}, "2020-12-23": {"count": 0, "versions": {}}, "2020-12-22": {"count": 0, "versions": {}}, "2020-07-26": {"count": 0, "versions": {}}, "2020-12-29": {"count": 0, "versions": {}}, "2020-12-28": {"count": 0, "versions": {}}, "2021-03-31": {"count": 0, "versions": {}}, "2021-03-30": {"count": 0, "versions": {}}, "2021-08-19": {"count": 37308, "versions": {"92.0a1": 574, "93.0a1": 6006, "92.0": 30728}}, "2019-12-14": {"count": 0, "versions": {}}, "2020-04-09": {"count": 0, "versions": {}}, "2021-01-28": {"count": 0, "versions": {}}, "2021-01-29": {"count": 0, "versions": {}}, "2020-11-08": {"count": 0, "versions": {}}, "2020-11-09": {"count": 0, "versions": {}}, "2020-11-06": {"count": 0, "versions": {}}, "2020-11-07": {"count": 0, "versions": {}}, "2020-11-04": {"count": 0, "versions": {}}, "2021-01-27": {"count": 0, "versions": {}}, "2020-11-02": {"count": 0, "versions": {}}, "2020-11-03": {"count": 0, "versions": {}}, "2021-01-22": {"count": 0, "versions": {}}, "2020-11-01": {"count": 0, "versions": {}}, "2021-05-15": {"count": 1, "versions": {"2021.02": 1}}, "2021-05-14": {"count": 4, "versions": {"2021.02": 4}}, "2021-05-17": {"count": 1, "versions": {"2021.02": 1}}, "2021-05-16": {"count": 1, "versions": {"2021.02": 1}}, "2021-05-11": {"count": 1, "versions": {"2021.02": 1}}, "2021-05-10": {"count": 0, "versions": {}}, "2021-05-13": {"count": 5, "versions": {"2021.02": 5}}, "2021-05-12": {"count": 3, "versions": {"2021.02": 3}}, "2021-05-19": {"count": 1, "versions": {"2021.02": 1}}, "2021-05-18": {"count": 1, "versions": {"2021.02": 1}}, "2019-10-18": {"count": 0, "versions": {}}, "2019-10-19": {"count": 0, "versions": {}}, "2019-10-12": {"count": 0, "versions": {}}, "2019-10-13": {"count": 0, "versions": {}}, "2019-10-10": {"count": 0, "versions": {}}, "2019-10-11": {"count": 0, "versions": {}}, "2019-10-16": {"count": 0, "versions": {}}, "2019-10-17": {"count": 0, "versions": {}}, "2019-10-14": {"count": 0, "versions": {}}, "2019-10-15": {"count": 0, "versions": {}}, "2021-09-24": {"count": 44581, "versions": {"94.0a1": 6019, "93.0a1": 171, "92.0a1": 43, "92.0": 1745, "93.0": 36603}}, "2021-09-25": {"count": 29674, "versions": {"94.0a1": 4901, "93.0a1": 155, "92.0a1": 58, "92.0": 1259, "93.0": 23301}}, "2021-04-29": {"count": 0, "versions": {}}, "2021-02-08": {"count": 0, "versions": {}}, "2021-09-20": {"count": 45863, "versions": {"94.0a1": 5973, "93.0a1": 249, "92.0a1": 52, "92.0": 3091, "93.0": 36498}}, "2021-09-21": {"count": 47278, "versions": {"94.0a1": 6286, "93.0a1": 279, "92.0a1": 61, "92.0": 2568, "93.0": 38084}}, "2021-09-22": {"count": 46826, "versions": {"2021.03": 1, "93.0a1": 250, "92.0a1": 72, "93.0": 37787, "94.0a1": 6526, "92.0": 2190}}, "2021-09-23": {"count": 45757, "versions": {"94.0a1": 6331, "93.0a1": 184, "92.0a1": 58, "92.0": 1990, "93.0": 37194}}, "2021-02-03": {"count": 0, "versions": {}}, "2021-02-02": {"count": 0, "versions": {}}, "2021-02-01": {"count": 0, "versions": {}}, "2021-04-20": {"count": 0, "versions": {}}, "2021-02-07": {"count": 0, "versions": {}}, "2021-02-06": {"count": 0, "versions": {}}, "2021-02-05": {"count": 0, "versions": {}}, "2021-02-04": {"count": 0, "versions": {}}, "2021-08-30": {"count": 43598, "versions": {"93.0a1": 6432, "92.0a1": 234, "92.0": 36932}}, "2021-08-31": {"count": 44609, "versions": {"93.0a1": 6488, "92.0a1": 260, "92.0": 37861}}, "2019-12-25": {"count": 0, "versions": {}}, "2019-12-24": {"count": 0, "versions": {}}, "2019-12-27": {"count": 0, "versions": {}}, "2019-12-26": {"count": 0, "versions": {}}, "2019-12-21": {"count": 0, "versions": {}}, "2019-12-20": {"count": 0, "versions": {}}, "2019-12-23": {"count": 0, "versions": {}}, "2019-12-22": {"count": 0, "versions": {}}, "2019-12-29": {"count": 0, "versions": {}}, "2019-12-28": {"count": 0, "versions": {}}, "2020-08-31": {"count": 0, "versions": {}}, "2020-08-30": {"count": 0, "versions": {}}, "2020-01-03": {"count": 0, "versions": {}}, "2020-01-02": {"count": 0, "versions": {}}, "2020-01-01": {"count": 0, "versions": {}}, "2020-01-07": {"count": 0, "versions": {}}, "2020-01-06": {"count": 0, "versions": {}}, "2020-01-05": {"count": 0, "versions": {}}, "2020-01-04": {"count": 0, "versions": {}}, "2020-06-02": {"count": 0, "versions": {}}, "2020-01-09": {"count": 0, "versions": {}}, "2020-01-08": {"count": 0, "versions": {}}, "2020-12-09": {"count": 0, "versions": {}}, "2019-11-08": {"count": 0, "versions": {}}, "2019-11-09": {"count": 0, "versions": {}}, "2019-11-06": {"count": 0, "versions": {}}, "2019-11-07": {"count": 0, "versions": {}}, "2019-11-04": {"count": 0, "versions": {}}, "2019-11-05": {"count": 0, "versions": {}}, "2019-11-02": {"count": 0, "versions": {}}, "2020-07-31": {"count": 0, "versions": {}}, "2019-11-01": {"count": 0, "versions": {}}, "2020-03-16": {"count": 0, "versions": {}}, "2020-03-17": {"count": 0, "versions": {}}, "2020-03-14": {"count": 0, "versions": {}}, "2020-03-15": {"count": 0, "versions": {}}, "2020-12-03": {"count": 0, "versions": {}}, "2020-03-13": {"count": 0, "versions": {}}, "2020-04-30": {"count": 0, "versions": {}}, "2020-12-01": {"count": 0, "versions": {}}, "2020-02-24": {"count": 0, "versions": {}}, "2020-02-25": {"count": 0, "versions": {}}, "2020-02-26": {"count": 0, "versions": {}}, "2020-02-27": {"count": 0, "versions": {}}, "2020-02-20": {"count": 0, "versions": {}}, "2020-02-21": {"count": 0, "versions": {}}, "2020-02-22": {"count": 0, "versions": {}}, "2020-02-23": {"count": 0, "versions": {}}, "2020-09-03": {"count": 0, "versions": {}}, "2020-09-02": {"count": 0, "versions": {}}, "2020-09-01": {"count": 0, "versions": {}}, "2020-02-28": {"count": 0, "versions": {}}, "2020-02-29": {"count": 0, "versions": {}}, "2020-09-05": {"count": 0, "versions": {}}, "2020-09-04": {"count": 0, "versions": {}}, "2020-03-30": {"count": 0, "versions": {}}, "2020-03-31": {"count": 0, "versions": {}}, "2020-06-20": {"count": 0, "versions": {}}, "2020-06-21": {"count": 0, "versions": {}}, "2020-06-22": {"count": 0, "versions": {}}, "2020-06-23": {"count": 0, "versions": {}}, "2020-06-24": {"count": 0, "versions": {}}, "2020-06-25": {"count": 0, "versions": {}}, "2020-06-26": {"count": 0, "versions": {}}, "2020-06-27": {"count": 0, "versions": {}}, "2020-06-28": {"count": 0, "versions": {}}, "2020-06-29": {"count": 0, "versions": {}}, "2019-11-03": {"count": 0, "versions": {}}, "2021-04-30": {"count": 0, "versions": {}}, "2020-06-01": {"count": 0, "versions": {}}, "2021-07-08": {"count": 0, "versions": {}}, "2021-07-09": {"count": 0, "versions": {}}, "2021-01-25": {"count": 0, "versions": {}}, "2021-07-05": {"count": 0, "versions": {}}, "2021-07-06": {"count": 0, "versions": {}}, "2021-07-07": {"count": 0, "versions": {}}, "2021-07-01": {"count": 0, "versions": {}}, "2021-07-02": {"count": 0, "versions": {}}, "2021-07-03": {"count": 0, "versions": {}}, "2020-05-09": {"count": 0, "versions": {}}, "2020-05-08": {"count": 0, "versions": {}}, "2020-05-07": {"count": 0, "versions": {}}, "2020-05-06": {"count": 0, "versions": {}}, "2020-05-05": {"count": 0, "versions": {}}, "2020-05-04": {"count": 0, "versions": {}}, "2020-05-03": {"count": 0, "versions": {}}, "2020-05-02": {"count": 0, "versions": {}}, "2020-05-01": {"count": 0, "versions": {}}, "2021-01-26": {"count": 0, "versions": {}}, "2021-04-12": {"count": 0, "versions": {}}, "2021-04-13": {"count": 0, "versions": {}}, "2021-04-10": {"count": 0, "versions": {}}, "2021-04-11": {"count": 0, "versions": {}}, "2021-04-16": {"count": 0, "versions": {}}, "2021-04-17": {"count": 0, "versions": {}}, "2021-04-14": {"count": 0, "versions": {}}, "2021-04-15": {"count": 0, "versions": {}}, "2021-04-18": {"count": 0, "versions": {}}, "2021-04-19": {"count": 0, "versions": {}}, "2020-10-09": {"count": 0, "versions": {}}, "2020-10-08": {"count": 0, "versions": {}}, "2021-01-20": {"count": 0, "versions": {}}, "2020-10-01": {"count": 0, "versions": {}}, "2020-10-03": {"count": 0, "versions": {}}, "2020-10-02": {"count": 0, "versions": {}}, "2020-10-05": {"count": 0, "versions": {}}, "2020-10-04": {"count": 0, "versions": {}}, "2020-10-07": {"count": 0, "versions": {}}, "2020-10-06": {"count": 0, "versions": {}}, "2019-09-09": {"count": 0, "versions": {}}, "2019-09-08": {"count": 0, "versions": {}}, "2021-06-29": {"count": 0, "versions": {}}, "2021-06-28": {"count": 0, "versions": {}}, "2019-09-03": {"count": 0, "versions": {}}, "2021-06-24": {"count": 0, "versions": {}}, "2021-06-27": {"count": 0, "versions": {}}, "2021-06-26": {"count": 0, "versions": {}}, "2019-09-07": {"count": 0, "versions": {}}, "2021-06-20": {"count": 0, "versions": {}}, "2019-09-05": {"count": 0, "versions": {}}, "2019-09-04": {"count": 0, "versions": {}}, "2021-04-25": {"count": 0, "versions": {}}, "2020-01-30": {"count": 0, "versions": {}}, "2020-01-31": {"count": 0, "versions": {}}, "2021-04-24": {"count": 0, "versions": {}}, "2021-03-01": {"count": 1, "versions": {"6852.0": 1}}, "2021-03-02": {"count": 0, "versions": {}}, "2021-03-03": {"count": 0, "versions": {}}, "2021-03-04": {"count": 0, "versions": {}}, "2021-03-05": {"count": 0, "versions": {}}, "2021-03-06": {"count": 0, "versions": {}}, "2021-03-07": {"count": 0, "versions": {}}, "2021-03-08": {"count": 0, "versions": {}}, "2021-03-09": {"count": 0, "versions": {}}, "2020-10-25": {"count": 0, "versions": {}}, "2020-10-24": {"count": 0, "versions": {}}, "2021-01-31": {"count": 0, "versions": {}}, "2021-01-30": {"count": 0, "versions": {}}, "2020-11-19": {"count": 0, "versions": {}}, "2020-11-18": {"count": 0, "versions": {}}, "2020-05-30": {"count": 0, "versions": {}}, "2020-05-31": {"count": 0, "versions": {}}, "2020-11-15": {"count": 0, "versions": {}}, "2020-11-14": {"count": 0, "versions": {}}, "2020-11-17": {"count": 0, "versions": {}}, "2020-11-16": {"count": 0, "versions": {}}, "2020-11-11": {"count": 0, "versions": {}}, "2020-11-10": {"count": 0, "versions": {}}, "2020-11-13": {"count": 0, "versions": {}}, "2020-11-12": {"count": 0, "versions": {}}, "2021-05-28": {"count": 1, "versions": {"2021.02": 1}}, "2021-05-29": {"count": 3, "versions": {"2021.02": 3}}, "2021-05-20": {"count": 1, "versions": {"2021.02": 1}}, "2021-05-21": {"count": 0, "versions": {}}, "2021-05-22": {"count": 0, "versions": {}}, "2021-05-23": {"count": 0, "versions": {}}, "2021-05-24": {"count": 0, "versions": {}}, "2021-05-25": {"count": 0, "versions": {}}, "2021-05-26": {"count": 0, "versions": {}}, "2021-05-27": {"count": 0, "versions": {}}, "2020-09-30": {"count": 0, "versions": {}}, "2021-06-06": {"count": 0, "versions": {}}, "2020-12-18": {"count": 0, "versions": {}}, "2020-12-19": {"count": 0, "versions": {}}, "2020-12-10": {"count": 0, "versions": {}}, "2020-12-11": {"count": 0, "versions": {}}, "2020-12-12": {"count": 0, "versions": {}}, "2020-12-13": {"count": 0, "versions": {}}, "2020-12-14": {"count": 0, "versions": {}}, "2020-12-15": {"count": 0, "versions": {}}, "2020-12-16": {"count": 0, "versions": {}}, "2020-12-17": {"count": 0, "versions": {}}, "2019-10-09": {"count": 0, "versions": {}}, "2019-10-08": {"count": 0, "versions": {}}, "2021-06-01": {"count": 0, "versions": {}}, "2019-10-01": {"count": 0, "versions": {}}, "2019-10-03": {"count": 0, "versions": {}}, "2019-10-02": {"count": 0, "versions": {}}, "2019-10-05": {"count": 0, "versions": {}}, "2019-10-04": {"count": 0, "versions": {}}, "2019-10-07": {"count": 0, "versions": {}}, "2019-10-06": {"count": 0, "versions": {}}, "2020-05-23": {"count": 0, "versions": {}}, "2019-12-18": {"count": 0, "versions": {}}, "2019-11-19": {"count": 0, "versions": {}}, "2021-08-27": {"count": 41787, "versions": {"93.0a1": 6364, "92.0a1": 288, "92.0": 35135}}, "2021-08-26": {"count": 43152, "versions": {"93.0a1": 6490, "92.0a1": 282, "92.0": 36380}}, "2021-08-25": {"count": 42259, "versions": {"92.0a1": 328, "93.0a1": 6471, "92.0": 35460}}, "2021-08-24": {"count": 42691, "versions": {"92.0a1": 291, "93.0a1": 6469, "92.0": 35931}}, "2021-08-23": {"count": 41276, "versions": {"93.0a1": 6291, "92.0a1": 337, "92.0": 34648}}, "2021-08-22": {"count": 24854, "versions": {"93.0a1": 4835, "92.0a1": 297, "92.0": 19722}}, "2021-08-21": {"count": 25635, "versions": {"93.0a1": 4875, "92.0a1": 449, "92.0": 20311}}, "2021-08-20": {"count": 36372, "versions": {"93.0a1": 5834, "92.0a1": 420, "92.0": 30118}}, "2021-06-08": {"count": 0, "versions": {}}, "2020-07-30": {"count": 0, "versions": {}}, "2021-08-29": {"count": 27331, "versions": {"93.0a1": 5345, "92.0a1": 221, "92.0": 21765}}, "2021-08-28": {"count": 28362, "versions": {"93.0a1": 5231, "92.0a1": 242, "92.0": 22889}}, "2020-08-01": {"count": 0, "versions": {}}, "2020-08-02": {"count": 0, "versions": {}}, "2020-08-03": {"count": 0, "versions": {}}, "2020-08-04": {"count": 0, "versions": {}}, "2020-08-05": {"count": 0, "versions": {}}, "2020-08-06": {"count": 0, "versions": {}}, "2020-08-07": {"count": 0, "versions": {}}, "2020-08-08": {"count": 0, "versions": {}}, "2020-08-09": {"count": 0, "versions": {}}, "2020-09-09": {"count": 0, "versions": {}}, "2020-09-08": {"count": 0, "versions": {}}, "2020-07-23": {"count": 0, "versions": {}}, "2020-07-22": {"count": 0, "versions": {}}, "2020-07-21": {"count": 0, "versions": {}}, "2020-07-20": {"count": 0, "versions": {}}, "2020-07-27": {"count": 0, "versions": {}}, "2019-11-18": {"count": 0, "versions": {}}, "2020-07-25": {"count": 0, "versions": {}}, "2020-07-24": {"count": 0, "versions": {}}, "2019-11-15": {"count": 0, "versions": {}}, "2019-11-14": {"count": 0, "versions": {}}, "2020-07-29": {"count": 0, "versions": {}}, "2020-07-28": {"count": 0, "versions": {}}, "2019-11-11": {"count": 0, "versions": {}}, "2019-11-10": {"count": 0, "versions": {}}, "2019-11-13": {"count": 0, "versions": {}}, "2019-11-12": {"count": 0, "versions": {}}, "2021-09-28": {"count": 48356, "versions": {"94.0a1": 6577, "93.0a1": 193, "92.0a1": 71, "92.0": 1496, "93.0": 40019}}, "2019-09-30": {"count": 0, "versions": {}}, "2020-09-07": {"count": 0, "versions": {}}, "2020-09-06": {"count": 0, "versions": {}}, "2020-04-04": {"count": 0, "versions": {}}, "2020-04-05": {"count": 0, "versions": {}}, "2020-04-06": {"count": 0, "versions": {}}, "2020-04-07": {"count": 0, "versions": {}}, "2020-04-01": {"count": 0, "versions": {}}, "2020-04-02": {"count": 0, "versions": {}}, "2020-04-03": {"count": 0, "versions": {}}, "2019-12-10": {"count": 0, "versions": {}}, "2019-12-11": {"count": 0, "versions": {}}, "2019-12-12": {"count": 0, "versions": {}}, "2019-12-13": {"count": 2, "versions": {"2016.2": 2}}, "2020-04-08": {"count": 0, "versions": {}}, "2019-12-15": {"count": 0, "versions": {}}, "2019-12-16": {"count": 0, "versions": {}}, "2019-12-17": {"count": 0, "versions": {}}, "2019-11-17": {"count": 0, "versions": {}}, "2020-03-27": {"count": 0, "versions": {}}, "2020-03-26": {"count": 0, "versions": {}}, "2020-03-25": {"count": 0, "versions": {}}, "2020-03-24": {"count": 0, "versions": {}}, "2020-03-23": {"count": 0, "versions": {}}, "2020-03-22": {"count": 0, "versions": {}}, "2020-03-21": {"count": 0, "versions": {}}, "2020-03-20": {"count": 0, "versions": {}}, "2019-11-16": {"count": 0, "versions": {}}, "2020-03-29": {"count": 0, "versions": {}}, "2020-03-28": {"count": 0, "versions": {}}, "2021-01-08": {"count": 0, "versions": {}}, "2021-01-09": {"count": 0, "versions": {}}, "2020-06-30": {"count": 0, "versions": {}}, "2021-01-02": {"count": 0, "versions": {}}, "2021-01-03": {"count": 0, "versions": {}}, "2021-01-01": {"count": 0, "versions": {}}, "2021-01-06": {"count": 0, "versions": {}}, "2021-01-07": {"count": 0, "versions": {}}, "2021-01-04": {"count": 0, "versions": {}}, "2021-01-05": {"count": 0, "versions": {}}, "2021-07-13": {"count": 1206, "versions": {"92.0a1": 1206}}, "2021-07-12": {"count": 1, "versions": {"92.0a1": 1}}, "2021-07-11": {"count": 0, "versions": {}}, "2021-07-10": {"count": 0, "versions": {}}, "2021-07-17": {"count": 4387, "versions": {"92.0a1": 4387}}, "2021-07-16": {"count": 5365, "versions": {"92.0a1": 5365}}, "2021-07-15": {"count": 5045, "versions": {"92.0a1": 5045}}, "2021-07-14": {"count": 4329, "versions": {"92.0a1": 4329}}, "2020-04-19": {"count": 0, "versions": {}}, "2021-07-19": {"count": 5814, "versions": {"92.0a1": 5814}}, "2021-07-18": {"count": 4432, "versions": {"92.0a1": 4432}}, "2019-10-31": {"count": 0, "versions": {}}, "2021-04-01": {"count": 0, "versions": {}}, "2021-02-23": {"count": 0, "versions": {}}, "2021-09-02": {"count": 45134, "versions": {"93.0a1": 6605, "92.0a1": 222, "92.0": 38307}}, "2021-09-03": {"count": 43373, "versions": {"93.0a1": 6159, "92.0a1": 225, "92.0": 36989}}, "2021-09-01": {"count": 45524, "versions": {"2021.03": 4, "93.0a1": 6536, "92.0a1": 240, "92.0": 38744}}, "2021-09-06": {"count": 44004, "versions": {"92.0a1": 169, "94.0a1": 18, "93.0a1": 5900, "92.0": 37917}}, "2021-09-07": {"count": 45321, "versions": {"94.0a1": 1114, "93.0a1": 5114, "92.0a1": 138, "92.0": 38951, "93.0": 4}}, "2021-09-04": {"count": 29410, "versions": {"93.0a1": 5203, "92.0a1": 187, "92.0": 24020}}, "2021-09-05": {"count": 27467, "versions": {"93.0a1": 5040, "92.0a1": 169, "92.0": 22258}}, "2021-02-25": {"count": 0, "versions": {}}, "2021-09-08": {"count": 46437, "versions": {"94.0a1": 3928, "93.0a1": 2463, "92.0a1": 118, "92.0": 39821, "93.0": 107}}, "2021-09-09": {"count": 46128, "versions": {"94.0a1": 4800, "93.0a1": 1645, "92.0a1": 110, "92.0": 39404, "93.0": 169}}, "2021-04-04": {"count": 0, "versions": {}}, "2021-02-21": {"count": 0, "versions": {}}, "2021-02-20": {"count": 0, "versions": {}}, "2021-04-03": {"count": 0, "versions": {}}, "2021-02-22": {"count": 0, "versions": {}}, "2021-04-05": {"count": 0, "versions": {}}, "2021-02-24": {"count": 0, "versions": {}}, "2021-02-27": {"count": 0, "versions": {}}, "2021-02-26": {"count": 0, "versions": {}}, "2021-04-09": {"count": 0, "versions": {}}, "2021-02-28": {"count": 0, "versions": {}}, "2021-04-06": {"count": 0, "versions": {}}, "2021-08-18": {"count": 35007, "versions": {"93.0a1": 5858, "92.0a1": 490, "92.0": 28659}}, "2021-04-08": {"count": 0, "versions": {}}, "2021-08-16": {"count": 19393, "versions": {"92.0a1": 666, "93.0a1": 5574, "92.0": 13153}}, "2021-08-17": {"count": 27298, "versions": {"93.0a1": 5786, "92.0a1": 562, "92.0": 20950}}, "2021-08-14": {"count": 8302, "versions": {"93.0a1": 4278, "92.0a1": 717, "92.0": 3307}}, "2021-08-15": {"count": 11157, "versions": {"93.0a1": 4288, "92.0a1": 644, "92.0": 6225}}, "2021-08-12": {"count": 6264, "versions": {"2021.03": 2, "93.0a1": 4905, "92.0a1": 1298, "92.0": 59}}, "2021-08-13": {"count": 6523, "versions": {"93.0a1": 4972, "92.0a1": 924, "92.0": 627}}, "2021-08-10": {"count": 6280, "versions": {"93.0a1": 1074, "92.0a1": 5206}}, "2021-02-09": {"count": 0, "versions": {}}, "2020-10-30": {"count": 0, "versions": {}}, "2020-10-31": {"count": 0, "versions": {}}, "2021-06-10": {"count": 0, "versions": {}}, "2021-06-11": {"count": 0, "versions": {}}, "2021-06-12": {"count": 0, "versions": {}}, "2021-06-13": {"count": 0, "versions": {}}, "2021-06-14": {"count": 0, "versions": {}}, "2021-06-15": {"count": 0, "versions": {}}, "2021-06-16": {"count": 0, "versions": {}}, "2021-06-17": {"count": 0, "versions": {}}, "2021-06-18": {"count": 0, "versions": {}}, "2021-06-19": {"count": 0, "versions": {}}, "2020-01-29": {"count": 0, "versions": {}}, "2020-01-28": {"count": 0, "versions": {}}, "2020-01-21": {"count": 0, "versions": {}}, "2020-01-20": {"count": 0, "versions": {}}, "2020-01-23": {"count": 0, "versions": {}}, "2020-01-22": {"count": 0, "versions": {}}, "2020-01-25": {"count": 0, "versions": {}}, "2020-01-24": {"count": 0, "versions": {}}, "2020-01-27": {"count": 0, "versions": {}}, "2020-01-26": {"count": 0, "versions": {}}, "2020-07-18": {"count": 0, "versions": {}}, "2020-07-19": {"count": 0, "versions": {}}, "2020-07-12": {"count": 0, "versions": {}}, "2020-07-13": {"count": 0, "versions": {}}, "2020-07-10": {"count": 0, "versions": {}}, "2020-07-11": {"count": 0, "versions": {}}, "2020-07-16": {"count": 0, "versions": {}}, "2020-07-17": {"count": 0, "versions": {}}, "2020-07-14": {"count": 0, "versions": {}}, "2020-07-15": {"count": 0, "versions": {}}, "2021-03-17": {"count": 0, "versions": {}}, "2021-03-16": {"count": 0, "versions": {}}, "2021-03-15": {"count": 0, "versions": {}}, "2021-03-14": {"count": 0, "versions": {}}, "2021-03-13": {"count": 0, "versions": {}}, "2021-03-12": {"count": 0, "versions": {}}, "2021-03-11": {"count": 0, "versions": {}}, "2021-03-10": {"count": 0, "versions": {}}, "2021-03-19": {"count": 0, "versions": {}}, "2021-03-18": {"count": 0, "versions": {}}, "2021-06-09": {"count": 0, "versions": {}}, "2021-04-07": {"count": 0, "versions": {}}, "2021-08-11": {"count": 6192, "versions": {"93.0a1": 4052, "92.0a1": 2112, "92.0": 28}}, "2020-11-20": {"count": 0, "versions": {}}, "2020-05-24": {"count": 0, "versions": {}}, "2020-05-27": {"count": 0, "versions": {}}, "2020-05-26": {"count": 2, "versions": {"683.10": 2}}, "2020-11-24": {"count": 1, "versions": {"2020.02.42": 1}}, "2020-05-20": {"count": 0, "versions": {}}, "2020-11-26": {"count": 0, "versions": {}}, "2020-05-22": {"count": 0, "versions": {}}, "2020-11-28": {"count": 0, "versions": {}}, "2020-11-29": {"count": 0, "versions": {}}, "2020-05-29": {"count": 0, "versions": {}}, "2020-05-28": {"count": 0, "versions": {}}, "2020-02-02": {"count": 0, "versions": {}}, "2020-02-03": {"count": 0, "versions": {}}, "2020-02-01": {"count": 0, "versions": {}}, "2020-02-06": {"count": 0, "versions": {}}, "2020-02-07": {"count": 0, "versions": {}}, "2020-02-04": {"count": 0, "versions": {}}, "2020-02-05": {"count": 0, "versions": {}}, "2020-02-08": {"count": 0, "versions": {}}, "2020-02-09": {"count": 0, "versions": {}}, "2019-12-19": {"count": 0, "versions": {}}, "2021-05-31": {"count": 0, "versions": {}}, "2021-05-30": {"count": 1, "versions": {"2021.02": 1}}, "2020-09-21": {"count": 0, "versions": {}}, "2020-09-20": {"count": 0, "versions": {}}, "2020-09-23": {"count": 0, "versions": {}}, "2020-09-22": {"count": 0, "versions": {}}, "2020-09-25": {"count": 0, "versions": {}}, "2020-09-24": {"count": 0, "versions": {}}, "2020-09-27": {"count": 0, "versions": {}}, "2020-09-26": {"count": 0, "versions": {}}, "2020-09-29": {"count": 0, "versions": {}}, "2020-09-28": {"count": 0, "versions": {}}, "2021-01-24": {"count": 0, "versions": {}}, "2020-03-18": {"count": 0, "versions": {}}, "2020-12-08": {"count": 0, "versions": {}}, "2020-12-07": {"count": 0, "versions": {}}, "2020-12-06": {"count": 0, "versions": {}}, "2020-12-05": {"count": 0, "versions": {}}, "2020-12-04": {"count": 0, "versions": {}}, "2020-03-12": {"count": 0, "versions": {}}, "2020-12-02": {"count": 0, "versions": {}}, "2020-03-10": {"count": 0, "versions": {}}, "2020-03-11": {"count": 0, "versions": {}}, "2020-11-05": {"count": 0, "versions": {}}, "2020-06-08": {"count": 0, "versions": {}}, "2020-06-09": {"count": 0, "versions": {}}, "2020-06-06": {"count": 0, "versions": {}}, "2020-06-07": {"count": 0, "versions": {}}, "2020-06-04": {"count": 0, "versions": {}}, "2020-06-05": {"count": 0, "versions": {}}, "2019-10-30": {"count": 0, "versions": {}}, "2020-06-03": {"count": 0, "versions": {}}, "2021-01-21": {"count": 0, "versions": {}}, "2019-09-22": {"count": 0, "versions": {}}, "2020-11-22": {"count": 0, "versions": {}}, "2021-01-23": {"count": 24, "versions": {"6891.1": 1, "681": 3, "68121.1": 7, "6871.1": 1, "6861.1": 2, "6804.1": 1, "6843.1": 7, "6851.1": 2}}, "2021-07-28": {"count": 6523, "versions": {"92.0a1": 6523}}, "2021-07-29": {"count": 6358, "versions": {"92.0a1": 6358}}, "2021-07-22": {"count": 6214, "versions": {"92.0a1": 6214}}, "2021-07-23": {"count": 6074, "versions": {"92.0a1": 6074}}, "2021-07-20": {"count": 6030, "versions": {"92.0a1": 6030}}, "2021-07-21": {"count": 6271, "versions": {"92.0a1": 6271}}, "2021-07-26": {"count": 6369, "versions": {"92.0a1": 6369}}, "2021-07-27": {"count": 6408, "versions": {"92.0a1": 6408}}, "2021-07-24": {"count": 5099, "versions": {"92.0a1": 5099}}, "2021-07-25": {"count": 5171, "versions": {"92.0a1": 5171}}, "2021-07-04": {"count": 0, "versions": {}}, "2019-09-28": {"count": 0, "versions": {}}, "2020-08-17": {"count": 0, "versions": {}}, "2020-08-16": {"count": 0, "versions": {}}, "2020-08-15": {"count": 0, "versions": {}}, "2020-08-14": {"count": 0, "versions": {}}, "2020-08-13": {"count": 0, "versions": {}}, "2020-08-12": {"count": 0, "versions": {}}, "2020-08-11": {"count": 0, "versions": {}}, "2020-08-10": {"count": 0, "versions": {}}, "2020-08-19": {"count": 0, "versions": {}}, "2020-08-18": {"count": 0, "versions": {}}, "2019-11-20": {"count": 0, "versions": {}}, "2019-11-21": {"count": 0, "versions": {}}, "2019-11-22": {"count": 0, "versions": {}}, "2019-11-23": {"count": 0, "versions": {}}, "2019-11-24": {"count": 0, "versions": {}}, "2019-11-25": {"count": 0, "versions": {}}, "2019-11-26": {"count": 0, "versions": {}}, "2019-11-27": {"count": 0, "versions": {}}, "2019-11-28": {"count": 0, "versions": {}}, "2019-11-29": {"count": 0, "versions": {}}, "2019-09-21": {"count": 0, "versions": {}}, "2019-09-20": {"count": 0, "versions": {}}, "2019-09-23": {"count": 0, "versions": {}}, "2020-04-18": {"count": 0, "versions": {}}, "2019-09-25": {"count": 0, "versions": {}}, "2019-09-24": {"count": 0, "versions": {}}, "2019-09-27": {"count": 0, "versions": {}}, "2019-09-26": {"count": 0, "versions": {}}, "2019-09-29": {"count": 0, "versions": {}}, "2020-04-12": {"count": 0, "versions": {}}, "2020-04-11": {"count": 0, "versions": {}}, "2020-04-10": {"count": 0, "versions": {}}, "2020-04-17": {"count": 0, "versions": {}}, "2020-04-16": {"count": 0, "versions": {}}, "2020-04-15": {"count": 0, "versions": {}}, "2020-04-14": {"count": 0, "versions": {}}, "2019-12-09": {"count": 0, "versions": {}}, "2019-12-08": {"count": 0, "versions": {}}, "2019-12-07": {"count": 0, "versions": {}}, "2019-12-06": {"count": 0, "versions": {}}, "2019-12-05": {"count": 0, "versions": {}}, "2019-12-04": {"count": 0, "versions": {}}, "2019-12-03": {"count": 0, "versions": {}}, "2019-12-02": {"count": 0, "versions": {}}, "2019-12-01": {"count": 0, "versions": {}}}